{
    "අභි.": {
        "title": "අභිධර්මයෙහි",
        "count": 213
    },
    "අතී.කෘද.": {
        "title": "අතීත කෘදන්තය",
        "count": 2
    },
    "අලං.": {
        "title": "අලංකාර ශාස්ත්‍රයෙහි",
        "count": 29
    },
    "අව්‍ය.": {
        "title": "අව්‍යය",
        "count": 24
    },
    "ආර්ථි.": {
        "title": "ආර්ථික විද්‍යාවෙහි",
        "count": 18
    },
    "උ.": {
        "title": "උපසර්ගය",
        "count": 22
    },
    "උඩ.": {
        "title": "උඩරට",
        "count": 1
    },
    "උද්භි.": {
        "title": "උද්භිද විද්‍යාවෙහි",
        "count": 81
    },
    "උමැද.": {
        "title": "උතුරු මැද පළාතෙහි",
        "count": 0
    },
    "කථා.": {
        "title": "කථා ව්‍යවහාරයෙහි",
        "count": 1778
    },
    "කමත්.": {
        "title": "කමත් ව්‍යවහාරයෙහි",
        "count": 18
    },
    "කායි.": {
        "title": "කායික විද්‍යාවෙහි",
        "count": 5
    },
    "ක්‍රි.": {
        "title": "ක්‍රියාපදය",
        "count": 3053
    },
    "ක්‍රි.වි.": {
        "title": "විශේෂණය",
        "count": 307
    },
    "ක්‍රිස්ති.": {
        "title": "ක්‍රිස්තියානි",
        "count": 145
    },
    "ගණිත.": {
        "title": "ගණිත ශාස්ත්‍රයෙහි",
        "count": 64
    },
    "ගොවි.": {
        "title": "ගොවි කර්මාන්තයෙහි",
        "count": 14
    },
    "ඡන්ද.": {
        "title": "ඡන්දස් ශාස්ත්‍රයෙහි",
        "count": 16
    },
    "ජීව.": {
        "title": "ජීව විද්‍යාවෙහි",
        "count": 12
    },
    "ජ්‍යාමිති.": {
        "title": "ජ්‍යාමිති ශාස්ත්‍රයෙහි",
        "count": 3
    },
    "ජ්‍යෝති.": {
        "title": "ජ්‍යෝතිෂ් ශාස්ත්‍රයෙහි",
        "count": 171
    },
    "තර්ක.": {
        "title": "තර්ක ශාස්ත්‍රයෙහි",
        "count": 18
    },
    "දර්ශන.": {
        "title": "දර්ශනයෙහි",
        "count": 45
    },
    "ධීව.": {
        "title": "ධීවර කර්මාන්තයෙහි",
        "count": 16
    },
    "නව.": {
        "title": "නව (නව්‍ය, නවීන) ව්‍යවහාරයෙහි",
        "count": 28
    },
    "නා.": {
        "title": "නාමපදය",
        "count": 29799
    },
    "නාට්‍ය.": {
        "title": "නාට්‍ය ශාස්ත්‍රයෙහි",
        "count": 2
    },
    "නා.ප්‍ර.": {
        "title": "නාම ප්‍රකෘතිය, ප්‍රකෘති රූපය",
        "count": 12898
    },
    "නා.ප්‍ර.බහු.": {
        "title": "නාම ප්‍රකෘති බහුවචන",
        "count": 34
    },
    "නා.බහු.": {
        "title": "නාමපද, බහුවචන",
        "count": 244
    },
    "නි.": {
        "title": "නිපාතය",
        "count": 135
    },
    "නීති.": {
        "title": "නීති ව්‍යවහාරයෙහි",
        "count": 63
    },
    "න්‍යාය.": {
        "title": "න්‍යාය ශාස්ත්‍රයෙහි",
        "count": 11
    },
    "පාරිභා.": {
        "title": "පාරිභාෂික ව්‍යවහාරයෙහි",
        "count": 5591
    },
    "පාරිභා.රසා.": {
        "title": "පාරිභාෂික ව්‍යවහාරය රසායන විද්‍යාව",
        "count": 0
    },
    "පරිග.": {
        "title": "පරිගණක විද්‍යාවෙහි",
        "count": 7
    },
    "පාත.": {
        "title": "පාතරට",
        "count": 0
    },
    "පූර්ව.ක්‍රි.": {
        "title": "පූර්ව ක්‍රියාව",
        "count": 13
    },
    "ප්‍ර.": {
        "title": "ප්‍රකෘතිය, ප්‍රකෘති රූපය",
        "count": 0
    },
    "ප්‍රත්‍ය.": {
        "title": "ප්‍රත්‍යය",
        "count": 4
    },
    "බහු.": {
        "title": "බහුවචන",
        "count": 1
    },
    "භා.දර්ශන.": {
        "title": "භාරතීය දර්ශනයෙහි",
        "count": 2
    },
    "භා.නා.": {
        "title": "භාවනාමය",
        "count": 6
    },
    "භූගෝ.": {
        "title": "භූගෝල විද්‍යාවෙහි",
        "count": 36
    },
    "භෞති.": {
        "title": "භෞතික විද්‍යාවෙහි",
        "count": 55
    },
    "භෞ.රසා.": {
        "title": "භෞතික රසායනයෙහි",
        "count": 0
    },
    "මැද.": {
        "title": "මැද පළාතෙහි",
        "count": 0
    },
    "රසා.": {
        "title": "රසායන විද්‍යාවෙහි",
        "count": 42
    },
    "රූඪි.": {
        "title": "රූඪ ව්‍යවහාරයෙහි",
        "count": 67
    },
    "රෝ.ක.": {
        "title": "රෝමානු කතෝලික",
        "count": 10
    },
    "වාස්තු.": {
        "title": "වාස්තු විද්‍යාවෙහි විශේෂණය",
        "count": 4
    },
    "වි.": {
        "title": "විශේෂණය",
        "count": 9189
    },
    "විද්‍යු.": {
        "title": "විද්‍යුතයෙහි, විද්‍යුත් විද්‍යාවෙහි",
        "count": 3
    },
    "විනය.": {
        "title": "විනයෙහි",
        "count": 94
    },
    "වෙ.": {
        "title": "වෙනුවට",
        "count": 0
    },
    "වෛද්‍ය.": {
        "title": "වෛද්‍ය ශාස්ත්‍රයෙහි",
        "count": 27
    },
    "ව්‍යාක.": {
        "title": "ව්‍යාකරණයෙහි",
        "count": 271
    },
    "සංගී.": {
        "title": "සංගීත ශාස්ත්‍රයෙහි",
        "count": 43
    },
    "සත්ව.": {
        "title": "සත්ත්ව විද්‍යාවෙහි",
        "count": 97
    },
    "සර්ව.": {
        "title": "සර්වනාම",
        "count": 39
    },
    "සර්ව.බහු.": {
        "title": "සර්වනාම බහුවචන",
        "count": 1
    },
    "හම්බ.": {
        "title": "හම්බන්තොට දිස්ත්‍රික්කයෙහි",
        "count": 0
    },
    "ළදරු.": {
        "title": "ළදරුබසෙහි",
        "count": 0
    }
}